mlsphere/__init__.py
mlsphere/cli/__init__.py
mlsphere/cli/mls.py
mlsphere/pkg/__init__.py
mlsphere/pkg/builder.py
mlsphere/pkg/runner.py
mlsphere/pkg/utils.py
mlsphere-0.0.5.data/scripts/mls.py
mlsphere-0.0.5.dist-info/METADATA
mlsphere-0.0.5.dist-info/WHEEL
mlsphere-0.0.5.dist-info/top_level.txt
mlsphere-0.0.5.dist-info/RECORD
